embersort/__init__.py
embersort/main.py
embersort-0.2.0.dist-info/WHEEL
embersort-0.2.0.dist-info/entry_points.txt
embersort-0.2.0.dist-info/METADATA
embersort-0.2.0.dist-info/RECORD
