Metadata-Version: 2.3
Name: embersort
Version: 0.2.0
Summary: A simple yet powerful Python module to automatically organize files into categorized folders.
Requires-Python: >=3.13
